tepracli/__init__.py
tepracli/__main__.py
tepracli/assets/ss3.ttf.gz
tepracli-1.1.1.dist-info/METADATA
tepracli-1.1.1.dist-info/WHEEL
tepracli-1.1.1.dist-info/entry_points.txt
tepracli-1.1.1.dist-info/top_level.txt
tepracli-1.1.1.dist-info/RECORD
