Metadata-Version: 2.4
Name: tepracli
Version: 1.1.1
Summary: An example of tepra-lite-esp32 client / CLI
Home-page: https://github.com/puhitaku/tepra-lite-esp32/tree/master/client
Author: Takumi Sueda
Author-email: puhitaku@gmail.com
License: MIT License
Classifier: Development Status :: 4 - Beta
Classifier: License :: OSI Approved :: MIT License
Classifier: Operating System :: OS Independent
Classifier: Programming Language :: Python
Classifier: Programming Language :: Python :: 3
Requires-Dist: click
Requires-Dist: pillow
Requires-Dist: qrcode[pil]
Requires-Dist: requests
Dynamic: author
Dynamic: author-email
Dynamic: classifier
Dynamic: description
Dynamic: description-content-type
Dynamic: home-page
Dynamic: license
Dynamic: requires-dist
Dynamic: summary
